keystoneclient_kerberos/__init__.py
keystoneclient_kerberos/v3.py
keystoneclient_kerberos/tests/__init__.py
keystoneclient_kerberos/tests/base.py
keystoneclient_kerberos/tests/test_federated.py
keystoneclient_kerberos/tests/test_v3.py
keystoneclient_kerberos/tests/utils.py
python_keystoneclient_kerberos-0.3.0.dist-info/DESCRIPTION.rst
python_keystoneclient_kerberos-0.3.0.dist-info/METADATA
python_keystoneclient_kerberos-0.3.0.dist-info/RECORD
python_keystoneclient_kerberos-0.3.0.dist-info/WHEEL
python_keystoneclient_kerberos-0.3.0.dist-info/entry_points.txt
python_keystoneclient_kerberos-0.3.0.dist-info/metadata.json
python_keystoneclient_kerberos-0.3.0.dist-info/pbr.json
python_keystoneclient_kerberos-0.3.0.dist-info/top_level.txt
