Metadata-Version: 2.0
Name: python-keystoneclient-kerberos
Version: 0.3.0
Summary: Kerberos authentication for the OpenStack clients
Home-page: http://www.openstack.org/
Author: OpenStack
Author-email: openstack-dev@lists.openstack.org
License: UNKNOWN
Platform: UNKNOWN
Classifier: Environment :: OpenStack
Classifier: Intended Audience :: Information Technology
Classifier: Intended Audience :: System Administrators
Classifier: License :: OSI Approved :: Apache Software License
Classifier: Operating System :: POSIX :: Linux
Classifier: Programming Language :: Python
Classifier: Programming Language :: Python :: 2
Classifier: Programming Language :: Python :: 2.7
Requires-Dist: keystoneauth1[kerberos] (>=2.1.0)
Requires-Dist: pbr (>=1.6)
Requires-Dist: requests-kerberos (>=0.6); (python_version=='2.7' or python_version=='2.6')
